devlprd/__init__.py
devlprd/__main__.py
devlprd/config.py
devlprd/daemon.py
devlprd/DaemonState.py
devlprd/filtering.py
devlprd/py.typed
devlprd/serif.py
devlprd-0.4.2.dist-info/LICENSE
devlprd-0.4.2.dist-info/WHEEL
devlprd-0.4.2.dist-info/METADATA
devlprd-0.4.2.dist-info/RECORD
