Metadata-Version: 2.1
Name: devlprd
Version: 0.4.2
Summary: Daemon for managing integrations with the FATNM DEVLPR
Home-page: https://github.com/FANTM/devlprd
License: MIT
Author: Ezra Boley
Author-email: eboley@wisc.edu
Requires-Python: >=3.7,<3.11
Classifier: License :: OSI Approved :: MIT License
Classifier: Programming Language :: Python :: 3
Classifier: Programming Language :: Python :: 3.7
Classifier: Programming Language :: Python :: 3.8
Classifier: Programming Language :: Python :: 3.9
Requires-Dist: mypy (>=0.910,<0.911)
Requires-Dist: numpy (>=1.21.2,<2.0.0)
Requires-Dist: pydevlpr-protocol (>=0.1.0,<0.2.0)
Requires-Dist: pyserial (>=3.5,<4.0)
Project-URL: Documentation, https://docs.getfantm.com
Project-URL: Repository, https://github.com/FANTM/devlprd
